multiply_test/__init__.py
multiply_test/multiplication.py
multiply_test-0.0.1.dist-info/METADATA
multiply_test-0.0.1.dist-info/WHEEL
multiply_test-0.0.1.dist-info/top_level.txt
multiply_test-0.0.1.dist-info/RECORD
